torminify/__init__.py
torminify/minify.py
torminify-0.1.4.dist-info/DESCRIPTION.rst
torminify-0.1.4.dist-info/METADATA
torminify-0.1.4.dist-info/RECORD
torminify-0.1.4.dist-info/WHEEL
torminify-0.1.4.dist-info/metadata.json
torminify-0.1.4.dist-info/top_level.txt
