Metadata-Version: 2.0
Name: torminify
Version: 0.1.4
Summary: Module for Tornado Web Framework, designed to automate minification of css and js files, easily implement asynchronous loading of scripts and additional stylesheets, and cache compiled tornado templates in memory
Home-page: https://github.com/PaulDiakov/torminify
Author: Paul Diakov
Author-email: paul.diakov@gmail.com
License: MIT
Platform: any
Requires-Dist: pyyaml
Requires-Dist: tornado
